SmartNqData/__init__.py
SmartNqData/api_client.py
SmartNqData/enums.py
SmartNqData/smart_nq_realtime.py
SmartNqData/utils.py
smartnqdata-0.4.0.dist-info/METADATA
smartnqdata-0.4.0.dist-info/WHEEL
smartnqdata-0.4.0.dist-info/top_level.txt
smartnqdata-0.4.0.dist-info/RECORD
