Metadata-Version: 2.4
Name: SmartNqData
Version: 0.4.0
Summary: An internal package to fetch market data from smartnq.com
Home-page: https://github.com/alirezakeyanjam/araTrade.Database
Author: Alireza Keyanjam
Author-email: akj@smartnq.com
Classifier: Programming Language :: Python :: 3
Classifier: License :: OSI Approved :: MIT License
Classifier: Operating System :: OS Independent
Requires-Python: >=3.6
Requires-Dist: requests
Requires-Dist: pandas
Requires-Dist: pytz
Requires-Dist: pika
Dynamic: author
Dynamic: author-email
Dynamic: classifier
Dynamic: description-content-type
Dynamic: home-page
Dynamic: requires-dist
Dynamic: requires-python
Dynamic: summary
